{
  "OKC-WAS-2026-03-21": {
    "status": "in",
    "clock": "9:16 - 4th",
    "away_score": "110",
    "home_score": "96",
    "team_stats": {
      "OKC": {
        "fieldGoalsMade-fieldGoalsAttempted": "43-75",
        "FG%": "57",
        "threePointFieldGoalsMade-threePointFieldGoalsAttempted": "11-25",
        "3P%": "44",
        "freeThrowsMade-freeThrowsAttempted": "13-20",
        "FT%": "65",
        "REB": "44",
        "OR": "13",
        "DR": "31",
        "AST": "26",
        "STL": "5",
        "BLK": "6",
        "TO": "12",
        "TTO": "0",
        "ToTO": "12",
        "TECH": "4",
        "FLAG": "0",
        "Points Conceded Off Turnovers": "12",
        "FBPs": "16",
        "PIP": "52",
        "PF": "15",
        "LL": "14",
        "LC": "15",
        "LPCT": "65"
      },
      "WAS": {
        "fieldGoalsMade-fieldGoalsAttempted": "34-74",
        "FG%": "46",
        "threePointFieldGoalsMade-threePointFieldGoalsAttempted": "15-31",
        "3P%": "48",
        "freeThrowsMade-freeThrowsAttempted": "13-18",
        "FT%": "72",
        "REB": "26",
        "OR": "7",
        "DR": "19",
        "AST": "25",
        "STL": "8",
        "BLK": "2",
        "TO": "11",
        "TTO": "0",
        "ToTO": "11",
        "TECH": "2",
        "FLAG": "0",
        "Points Conceded Off Turnovers": "15",
        "FBPs": "18",
        "PIP": "30",
        "PF": "19",
        "LL": "5",
        "LC": "15",
        "LPCT": "21"
      }
    },
    "players": {
      "WAS": {
        "Justin Champagnie": {
          "MIN": 14,
          "PTS": "3",
          "REB": "1",
          "AST": "1",
          "STL": "1",
          "BLK": "0",
          "TO": "0",
          "FG": "1-3",
          "3PT": "1-1",
          "FT": "0-0",
          "fd_pts": 8.7,
          "dk_pts": 8.25,
          "is_on_court": false
        },
        "Alex Sarr": {
          "MIN": 22,
          "PTS": "14",
          "REB": "5",
          "AST": "8",
          "STL": "1",
          "BLK": "1",
          "TO": "3",
          "FG": "5-12",
          "3PT": "2-5",
          "FT": "2-2",
          "fd_pts": 35.0,
          "dk_pts": 35.75,
          "is_on_court": false
        },
        "Bub Carrington": {
          "MIN": 23,
          "PTS": "14",
          "REB": "2",
          "AST": "3",
          "STL": "0",
          "BLK": "0",
          "TO": "2",
          "FG": "5-9",
          "3PT": "3-6",
          "FT": "1-3",
          "fd_pts": 18.9,
          "dk_pts": 21.5,
          "is_on_court": true
        },
        "Bilal Coulibaly": {
          "MIN": 26,
          "PTS": "19",
          "REB": "3",
          "AST": "3",
          "STL": "1",
          "BLK": "1",
          "TO": "0",
          "FG": "7-14",
          "3PT": "3-5",
          "FT": "2-2",
          "fd_pts": 33.1,
          "dk_pts": 32.75,
          "is_on_court": false
        },
        "Will Riley": {
          "MIN": 25,
          "PTS": "9",
          "REB": "1",
          "AST": "3",
          "STL": "0",
          "BLK": "0",
          "TO": "3",
          "FG": "3-7",
          "3PT": "0-1",
          "FT": "3-3",
          "fd_pts": 11.7,
          "dk_pts": 13.25,
          "is_on_court": false
        },
        "Anthony Gill": {
          "MIN": 20,
          "PTS": "7",
          "REB": "5",
          "AST": "1",
          "STL": "2",
          "BLK": "0",
          "TO": "0",
          "FG": "3-6",
          "3PT": "0-1",
          "FT": "1-1",
          "fd_pts": 20.5,
          "dk_pts": 18.75,
          "is_on_court": false
        },
        "Tristan Vukcevic": {
          "MIN": 16,
          "PTS": "6",
          "REB": "5",
          "AST": "0",
          "STL": "0",
          "BLK": "0",
          "TO": "2",
          "FG": "2-8",
          "3PT": "1-5",
          "FT": "1-3",
          "fd_pts": 10.0,
          "dk_pts": 11.75,
          "is_on_court": true
        },
        "Sharife Cooper": {
          "MIN": 12,
          "PTS": "3",
          "REB": "1",
          "AST": "2",
          "STL": "1",
          "BLK": "0",
          "TO": "0",
          "FG": "1-4",
          "3PT": "1-1",
          "FT": "0-0",
          "fd_pts": 10.2,
          "dk_pts": 9.75,
          "is_on_court": true
        },
        "Jamir Watkins": {
          "MIN": 20,
          "PTS": "13",
          "REB": "3",
          "AST": "3",
          "STL": "2",
          "BLK": "0",
          "TO": "0",
          "FG": "4-7",
          "3PT": "2-4",
          "FT": "3-4",
          "fd_pts": 27.1,
          "dk_pts": 26.25,
          "is_on_court": true
        },
        "Jaden Hardy": {
          "MIN": 14,
          "PTS": "8",
          "REB": "0",
          "AST": "1",
          "STL": "0",
          "BLK": "0",
          "TO": "1",
          "FG": "3-4",
          "3PT": "2-2",
          "FT": "0-0",
          "fd_pts": 8.5,
          "dk_pts": 10.0,
          "is_on_court": true
        }
      },
      "OKC": {
        "Isaiah Hartenstein": {
          "MIN": 21,
          "PTS": "8",
          "REB": "15",
          "AST": "7",
          "STL": "2",
          "BLK": "0",
          "TO": "2",
          "FG": "4-5",
          "3PT": "0-0",
          "FT": "0-2",
          "fd_pts": 40.5,
          "dk_pts": 40.25,
          "is_on_court": true
        },
        "Chet Holmgren": {
          "MIN": 22,
          "PTS": "14",
          "REB": "8",
          "AST": "0",
          "STL": "0",
          "BLK": "2",
          "TO": "1",
          "FG": "5-8",
          "3PT": "0-1",
          "FT": "4-4",
          "fd_pts": 28.6,
          "dk_pts": 27.5,
          "is_on_court": true
        },
        "Shai Gilgeous-Alexander": {
          "MIN": 30,
          "PTS": "36",
          "REB": "3",
          "AST": "6",
          "STL": "1",
          "BLK": "0",
          "TO": "2",
          "FG": "15-25",
          "3PT": "1-2",
          "FT": "5-8",
          "fd_pts": 49.6,
          "dk_pts": 50.25,
          "is_on_court": false
        },
        "Cason Wallace": {
          "MIN": 15,
          "PTS": "4",
          "REB": "2",
          "AST": "3",
          "STL": "0",
          "BLK": "0",
          "TO": "0",
          "FG": "1-2",
          "3PT": "0-1",
          "FT": "2-2",
          "fd_pts": 10.9,
          "dk_pts": 11.0,
          "is_on_court": false
        },
        "Ajay Mitchell": {
          "MIN": 15,
          "PTS": "14",
          "REB": "1",
          "AST": "3",
          "STL": "1",
          "BLK": "0",
          "TO": "1",
          "FG": "6-10",
          "3PT": "2-2",
          "FT": "0-0",
          "fd_pts": 21.7,
          "dk_pts": 22.25,
          "is_on_court": false
        },
        "Jaylin Williams": {
          "MIN": 9,
          "PTS": "0",
          "REB": "3",
          "AST": "0",
          "STL": "0",
          "BLK": "1",
          "TO": "0",
          "FG": "0-1",
          "3PT": "0-1",
          "FT": "0-0",
          "fd_pts": 6.6,
          "dk_pts": 5.75,
          "is_on_court": false
        },
        "Brooks Barnhizer": {
          "MIN": 2,
          "PTS": "0",
          "REB": "1",
          "AST": "0",
          "STL": "0",
          "BLK": "0",
          "TO": "0",
          "FG": "0-0",
          "3PT": "0-0",
          "FT": "0-0",
          "fd_pts": 1.2,
          "dk_pts": 1.25,
          "is_on_court": false
        },
        "Alex Caruso": {
          "MIN": 18,
          "PTS": "4",
          "REB": "1",
          "AST": "5",
          "STL": "1",
          "BLK": "2",
          "TO": "1",
          "FG": "2-4",
          "3PT": "0-2",
          "FT": "0-0",
          "fd_pts": 20.7,
          "dk_pts": 18.25,
          "is_on_court": true
        },
        "Kenrich Williams": {
          "MIN": 5,
          "PTS": "7",
          "REB": "1",
          "AST": "0",
          "STL": "0",
          "BLK": "0",
          "TO": "0",
          "FG": "2-3",
          "3PT": "1-2",
          "FT": "2-4",
          "fd_pts": 8.2,
          "dk_pts": 8.75,
          "is_on_court": false
        },
        "Isaiah Joe": {
          "MIN": 21,
          "PTS": "6",
          "REB": "4",
          "AST": "2",
          "STL": "0",
          "BLK": "0",
          "TO": "1",
          "FG": "2-6",
          "3PT": "2-6",
          "FT": "0-0",
          "fd_pts": 12.8,
          "dk_pts": 14.5,
          "is_on_court": true
        },
        "Aaron Wiggins": {
          "MIN": 14,
          "PTS": "5",
          "REB": "2",
          "AST": "0",
          "STL": "0",
          "BLK": "0",
          "TO": "4",
          "FG": "2-2",
          "3PT": "1-1",
          "FT": "0-0",
          "fd_pts": 3.4,
          "dk_pts": 6.0,
          "is_on_court": false
        },
        "Jared McCain": {
          "MIN": 19,
          "PTS": "12",
          "REB": "3",
          "AST": "0",
          "STL": "0",
          "BLK": "1",
          "TO": "0",
          "FG": "4-9",
          "3PT": "4-7",
          "FT": "0-0",
          "fd_pts": 18.6,
          "dk_pts": 19.75,
          "is_on_court": true
        }
      }
    },
    "recent_plays": [
      {
        "time": "Q4 9:17",
        "text": "Isaiah Hartenstein defensive rebound"
      },
      {
        "time": "Q4 9:20",
        "text": "Jamir Watkins misses driving layup"
      },
      {
        "time": "Q4 9:34",
        "text": "Bub Carrington enters the game for Will Riley"
      },
      {
        "time": "Q4 9:34",
        "text": "Wizards defensive team rebound"
      },
      {
        "time": "Q4 9:37",
        "text": "Isaiah Joe misses 23-foot three point jumper"
      }
    ]
  },
  "MEM-CHA-2026-03-21": {
    "status": "in",
    "clock": "10:22 - 1st",
    "away_score": "6",
    "home_score": "6",
    "team_stats": {
      "MEM": {
        "fieldGoalsMade-fieldGoalsAttempted": "2-3",
        "FG%": "67",
        "threePointFieldGoalsMade-threePointFieldGoalsAttempted": "2-3",
        "3P%": "67",
        "freeThrowsMade-freeThrowsAttempted": "0-0",
        "FT%": "0",
        "REB": "1",
        "OR": "1",
        "DR": "0",
        "AST": "1",
        "STL": "0",
        "BLK": "0",
        "TO": "1",
        "TTO": "0",
        "ToTO": "1",
        "TECH": "0",
        "FLAG": "0",
        "Points Conceded Off Turnovers": "0",
        "FBPs": "0",
        "PIP": "0",
        "PF": "0",
        "LL": "0",
        "LC": "0",
        "LPCT": "0"
      },
      "CHA": {
        "fieldGoalsMade-fieldGoalsAttempted": "2-3",
        "FG%": "67",
        "threePointFieldGoalsMade-threePointFieldGoalsAttempted": "2-2",
        "3P%": "100",
        "freeThrowsMade-freeThrowsAttempted": "0-0",
        "FT%": "0",
        "REB": "1",
        "OR": "1",
        "DR": "0",
        "AST": "1",
        "STL": "1",
        "BLK": "0",
        "TO": "1",
        "TTO": "0",
        "ToTO": "1",
        "TECH": "0",
        "FLAG": "0",
        "Points Conceded Off Turnovers": "3",
        "FBPs": "0",
        "PIP": "0",
        "PF": "0",
        "LL": "3",
        "LC": "0",
        "LPCT": "71"
      }
    },
    "players": {
      "CHA": {
        "Miles Bridges": {
          "MIN": 2,
          "PTS": "0",
          "REB": "0",
          "AST": "0",
          "STL": "0",
          "BLK": "0",
          "TO": "0",
          "FG": "0-0",
          "3PT": "0-0",
          "FT": "0-0",
          "fd_pts": 0.0,
          "dk_pts": 0.0,
          "is_on_court": false
        },
        "Moussa Diabate": {
          "MIN": 2,
          "PTS": "0",
          "REB": "1",
          "AST": "1",
          "STL": "0",
          "BLK": "0",
          "TO": "0",
          "FG": "0-0",
          "3PT": "0-0",
          "FT": "0-0",
          "fd_pts": 2.7,
          "dk_pts": 2.75,
          "is_on_court": false
        },
        "Brandon Miller": {
          "MIN": 2,
          "PTS": "0",
          "REB": "0",
          "AST": "0",
          "STL": "0",
          "BLK": "0",
          "TO": "0",
          "FG": "0-0",
          "3PT": "0-0",
          "FT": "0-0",
          "fd_pts": 0.0,
          "dk_pts": 0.0,
          "is_on_court": false
        },
        "LaMelo Ball": {
          "MIN": 2,
          "PTS": "6",
          "REB": "0",
          "AST": "0",
          "STL": "1",
          "BLK": "0",
          "TO": "0",
          "FG": "2-3",
          "3PT": "2-2",
          "FT": "0-0",
          "fd_pts": 9.0,
          "dk_pts": 9.0,
          "is_on_court": false
        },
        "Kon Knueppel": {
          "MIN": 2,
          "PTS": "0",
          "REB": "0",
          "AST": "0",
          "STL": "0",
          "BLK": "0",
          "TO": "1",
          "FG": "0-0",
          "3PT": "0-0",
          "FT": "0-0",
          "fd_pts": -1.0,
          "dk_pts": -0.5,
          "is_on_court": false
        }
      },
      "MEM": {
        "Olivier-Maxence Prosper": {
          "MIN": 2,
          "PTS": "0",
          "REB": "1",
          "AST": "0",
          "STL": "0",
          "BLK": "0",
          "TO": "0",
          "FG": "0-0",
          "3PT": "0-0",
          "FT": "0-0",
          "fd_pts": 1.2,
          "dk_pts": 1.25,
          "is_on_court": false
        },
        "GG Jackson": {
          "MIN": 2,
          "PTS": "0",
          "REB": "0",
          "AST": "0",
          "STL": "0",
          "BLK": "0",
          "TO": "0",
          "FG": "0-0",
          "3PT": "0-0",
          "FT": "0-0",
          "fd_pts": 0.0,
          "dk_pts": 0.0,
          "is_on_court": false
        },
        "Jaylen Wells": {
          "MIN": 2,
          "PTS": "3",
          "REB": "0",
          "AST": "0",
          "STL": "0",
          "BLK": "0",
          "TO": "0",
          "FG": "1-1",
          "3PT": "1-1",
          "FT": "0-0",
          "fd_pts": 3.0,
          "dk_pts": 3.5,
          "is_on_court": false
        },
        "Javon Small": {
          "MIN": 2,
          "PTS": "3",
          "REB": "0",
          "AST": "1",
          "STL": "0",
          "BLK": "0",
          "TO": "1",
          "FG": "1-1",
          "3PT": "1-1",
          "FT": "0-0",
          "fd_pts": 3.5,
          "dk_pts": 4.5,
          "is_on_court": false
        },
        "Walter Clayton Jr.": {
          "MIN": 2,
          "PTS": "0",
          "REB": "0",
          "AST": "0",
          "STL": "0",
          "BLK": "0",
          "TO": "0",
          "FG": "0-1",
          "3PT": "0-1",
          "FT": "0-0",
          "fd_pts": 0.0,
          "dk_pts": 0.0,
          "is_on_court": false
        }
      }
    },
    "recent_plays": [
      {
        "time": "Q1 10:41",
        "text": "Kon Knueppel steps out of bounds turnover"
      },
      {
        "time": "Q1 10:45",
        "text": "Javon Small bad pass\nturnover (LaMelo Ball steals)"
      },
      {
        "time": "Q1 11:02",
        "text": "LaMelo Ball makes 27-foot three pointer"
      },
      {
        "time": "Q1 11:11",
        "text": "Jaylen Wells makes 22-foot three point jumper (Javon Small assists)"
      },
      {
        "time": "Q1 11:14",
        "text": "Olivier-Maxence Prosper offensive rebound"
      }
    ]
  },
  "LAL-ORL-2026-03-21": {
    "status": "in",
    "clock": "10:16 - 1st",
    "away_score": "6",
    "home_score": "3",
    "team_stats": {
      "LAL": {
        "fieldGoalsMade-fieldGoalsAttempted": "3-4",
        "FG%": "75",
        "threePointFieldGoalsMade-threePointFieldGoalsAttempted": "0-1",
        "3P%": "0",
        "freeThrowsMade-freeThrowsAttempted": "0-0",
        "FT%": "0",
        "REB": "1",
        "OR": "0",
        "DR": "1",
        "AST": "2",
        "STL": "2",
        "BLK": "0",
        "TO": "0",
        "TTO": "0",
        "ToTO": "0",
        "TECH": "0",
        "FLAG": "0",
        "Points Conceded Off Turnovers": "0",
        "FBPs": "4",
        "PIP": "6",
        "PF": "0",
        "LL": "6",
        "LC": "0",
        "LPCT": "85"
      },
      "ORL": {
        "fieldGoalsMade-fieldGoalsAttempted": "0-1",
        "FG%": "0",
        "threePointFieldGoalsMade-threePointFieldGoalsAttempted": "0-0",
        "3P%": "0",
        "freeThrowsMade-freeThrowsAttempted": "0-0",
        "FT%": "0",
        "REB": "1",
        "OR": "0",
        "DR": "1",
        "AST": "0",
        "STL": "0",
        "BLK": "0",
        "TO": "2",
        "TTO": "0",
        "ToTO": "2",
        "TECH": "0",
        "FLAG": "0",
        "Points Conceded Off Turnovers": "4",
        "FBPs": "0",
        "PIP": "0",
        "PF": "0",
        "LL": "0",
        "LC": "0",
        "LPCT": "0"
      }
    },
    "players": {
      "ORL": {
        "Paolo Banchero": {
          "MIN": 1,
          "PTS": "0",
          "REB": "0",
          "AST": "0",
          "STL": "0",
          "BLK": "0",
          "TO": "1",
          "FG": "0-0",
          "3PT": "0-0",
          "FT": "0-0",
          "fd_pts": -1.0,
          "dk_pts": -0.5,
          "is_on_court": false
        },
        "Tristan da Silva": {
          "MIN": 1,
          "PTS": "0",
          "REB": "0",
          "AST": "0",
          "STL": "0",
          "BLK": "0",
          "TO": "0",
          "FG": "0-0",
          "3PT": "0-0",
          "FT": "0-0",
          "fd_pts": 0.0,
          "dk_pts": 0.0,
          "is_on_court": false
        },
        "Wendell Carter Jr.": {
          "MIN": 1,
          "PTS": "0",
          "REB": "0",
          "AST": "0",
          "STL": "0",
          "BLK": "0",
          "TO": "0",
          "FG": "0-1",
          "3PT": "0-0",
          "FT": "0-0",
          "fd_pts": 0.0,
          "dk_pts": 0.0,
          "is_on_court": false
        },
        "Desmond Bane": {
          "MIN": 2,
          "PTS": "0",
          "REB": "1",
          "AST": "0",
          "STL": "0",
          "BLK": "0",
          "TO": "1",
          "FG": "0-0",
          "3PT": "0-0",
          "FT": "0-0",
          "fd_pts": 0.2,
          "dk_pts": 0.75,
          "is_on_court": false
        },
        "Jalen Suggs": {
          "MIN": 1,
          "PTS": "0",
          "REB": "0",
          "AST": "0",
          "STL": "0",
          "BLK": "0",
          "TO": "0",
          "FG": "0-0",
          "3PT": "0-0",
          "FT": "0-0",
          "fd_pts": 0.0,
          "dk_pts": 0.0,
          "is_on_court": false
        }
      },
      "LAL": {
        "LeBron James": {
          "MIN": 1,
          "PTS": "2",
          "REB": "1",
          "AST": "0",
          "STL": "2",
          "BLK": "0",
          "TO": "0",
          "FG": "1-1",
          "3PT": "0-0",
          "FT": "0-0",
          "fd_pts": 9.2,
          "dk_pts": 7.25,
          "is_on_court": false
        },
        "Deandre Ayton": {
          "MIN": 1,
          "PTS": "2",
          "REB": "0",
          "AST": "0",
          "STL": "0",
          "BLK": "0",
          "TO": "0",
          "FG": "1-1",
          "3PT": "0-0",
          "FT": "0-0",
          "fd_pts": 2.0,
          "dk_pts": 2.0,
          "is_on_court": false
        },
        "Marcus Smart": {
          "MIN": 1,
          "PTS": "0",
          "REB": "0",
          "AST": "0",
          "STL": "0",
          "BLK": "0",
          "TO": "0",
          "FG": "0-0",
          "3PT": "0-0",
          "FT": "0-0",
          "fd_pts": 0.0,
          "dk_pts": 0.0,
          "is_on_court": false
        },
        "Luka Doncic": {
          "MIN": 2,
          "PTS": "2",
          "REB": "0",
          "AST": "0",
          "STL": "0",
          "BLK": "0",
          "TO": "0",
          "FG": "1-2",
          "3PT": "0-1",
          "FT": "0-0",
          "fd_pts": 2.0,
          "dk_pts": 2.0,
          "is_on_court": false
        },
        "Austin Reaves": {
          "MIN": 1,
          "PTS": "0",
          "REB": "0",
          "AST": "2",
          "STL": "0",
          "BLK": "0",
          "TO": "0",
          "FG": "0-0",
          "3PT": "0-0",
          "FT": "0-0",
          "fd_pts": 3.0,
          "dk_pts": 3.0,
          "is_on_court": false
        }
      }
    },
    "recent_plays": [
      {
        "time": "Q1 10:24",
        "text": "Desmond Bane defensive rebound"
      },
      {
        "time": "Q1 10:27",
        "text": "Luka Doncic misses 26-foot three point step back jumpshot"
      },
      {
        "time": "Q1 10:38",
        "text": "LeBron James defensive rebound"
      },
      {
        "time": "Q1 10:41",
        "text": "Wendell Carter Jr. misses 8-foot two point shot"
      },
      {
        "time": "Q1 11:05",
        "text": "Luka Doncic makes running layup"
      }
    ]
  },
  "CLE-NOP-2026-03-21": {
    "status": "in",
    "clock": "10:19 - 1st",
    "away_score": "5",
    "home_score": "2",
    "team_stats": {
      "CLE": {
        "fieldGoalsMade-fieldGoalsAttempted": "2-3",
        "FG%": "67",
        "threePointFieldGoalsMade-threePointFieldGoalsAttempted": "1-1",
        "3P%": "100",
        "freeThrowsMade-freeThrowsAttempted": "0-0",
        "FT%": "0",
        "REB": "2",
        "OR": "0",
        "DR": "2",
        "AST": "2",
        "STL": "0",
        "BLK": "0",
        "TO": "0",
        "TTO": "0",
        "ToTO": "0",
        "TECH": "0",
        "FLAG": "0",
        "Points Conceded Off Turnovers": "0",
        "FBPs": "0",
        "PIP": "2",
        "PF": "0",
        "LL": "3",
        "LC": "0",
        "LPCT": "81"
      },
      "NOP": {
        "fieldGoalsMade-fieldGoalsAttempted": "1-3",
        "FG%": "33",
        "threePointFieldGoalsMade-threePointFieldGoalsAttempted": "0-2",
        "3P%": "0",
        "freeThrowsMade-freeThrowsAttempted": "0-0",
        "FT%": "0",
        "REB": "1",
        "OR": "0",
        "DR": "1",
        "AST": "1",
        "STL": "0",
        "BLK": "1",
        "TO": "0",
        "TTO": "0",
        "ToTO": "0",
        "TECH": "0",
        "FLAG": "0",
        "Points Conceded Off Turnovers": "0",
        "FBPs": "0",
        "PIP": "2",
        "PF": "1",
        "LL": "0",
        "LC": "0",
        "LPCT": "0"
      }
    },
    "players": {
      "NOP": {
        "Herbert Jones": {
          "MIN": 1,
          "PTS": "0",
          "REB": "0",
          "AST": "0",
          "STL": "0",
          "BLK": "0",
          "TO": "0",
          "FG": "0-1",
          "3PT": "0-1",
          "FT": "0-0",
          "fd_pts": 0.0,
          "dk_pts": 0.0,
          "is_on_court": false
        },
        "Zion Williamson": {
          "MIN": 1,
          "PTS": "0",
          "REB": "1",
          "AST": "0",
          "STL": "0",
          "BLK": "0",
          "TO": "0",
          "FG": "0-0",
          "3PT": "0-0",
          "FT": "0-0",
          "fd_pts": 1.2,
          "dk_pts": 1.25,
          "is_on_court": false
        },
        "Trey Murphy III": {
          "MIN": 1,
          "PTS": "0",
          "REB": "0",
          "AST": "0",
          "STL": "0",
          "BLK": "1",
          "TO": "0",
          "FG": "0-0",
          "3PT": "0-0",
          "FT": "0-0",
          "fd_pts": 3.0,
          "dk_pts": 2.0,
          "is_on_court": false
        },
        "Dejounte Murray": {
          "MIN": 2,
          "PTS": "0",
          "REB": "0",
          "AST": "1",
          "STL": "1",
          "BLK": "0",
          "TO": "0",
          "FG": "0-0",
          "3PT": "0-0",
          "FT": "0-0",
          "fd_pts": 4.5,
          "dk_pts": 3.5,
          "is_on_court": false
        },
        "Saddiq Bey": {
          "MIN": 1,
          "PTS": "2",
          "REB": "0",
          "AST": "0",
          "STL": "0",
          "BLK": "0",
          "TO": "0",
          "FG": "1-2",
          "3PT": "0-1",
          "FT": "0-0",
          "fd_pts": 2.0,
          "dk_pts": 2.0,
          "is_on_court": false
        }
      },
      "CLE": {
        "Dean Wade": {
          "MIN": 1,
          "PTS": "0",
          "REB": "0",
          "AST": "1",
          "STL": "0",
          "BLK": "0",
          "TO": "0",
          "FG": "0-0",
          "3PT": "0-0",
          "FT": "0-0",
          "fd_pts": 1.5,
          "dk_pts": 1.5,
          "is_on_court": false
        },
        "Evan Mobley": {
          "MIN": 1,
          "PTS": "0",
          "REB": "0",
          "AST": "0",
          "STL": "0",
          "BLK": "0",
          "TO": "0",
          "FG": "0-0",
          "3PT": "0-0",
          "FT": "0-0",
          "fd_pts": 0.0,
          "dk_pts": 0.0,
          "is_on_court": false
        },
        "James Harden": {
          "MIN": 2,
          "PTS": "0",
          "REB": "0",
          "AST": "1",
          "STL": "0",
          "BLK": "0",
          "TO": "1",
          "FG": "0-0",
          "3PT": "0-0",
          "FT": "0-0",
          "fd_pts": 0.5,
          "dk_pts": 1.0,
          "is_on_court": false
        },
        "Donovan Mitchell": {
          "MIN": 1,
          "PTS": "2",
          "REB": "2",
          "AST": "0",
          "STL": "0",
          "BLK": "0",
          "TO": "0",
          "FG": "1-2",
          "3PT": "0-0",
          "FT": "0-0",
          "fd_pts": 4.4,
          "dk_pts": 4.5,
          "is_on_court": false
        },
        "Sam Merrill": {
          "MIN": 1,
          "PTS": "3",
          "REB": "0",
          "AST": "0",
          "STL": "0",
          "BLK": "0",
          "TO": "0",
          "FG": "1-1",
          "3PT": "1-1",
          "FT": "0-0",
          "fd_pts": 3.0,
          "dk_pts": 3.5,
          "is_on_court": false
        }
      }
    },
    "recent_plays": [
      {
        "time": "Q1 10:31",
        "text": "Donovan Mitchell defensive rebound"
      },
      {
        "time": "Q1 10:33",
        "text": "Saddiq Bey misses 25-foot running jump shot"
      },
      {
        "time": "Q1 10:36",
        "text": "Zion Williamson defensive rebound"
      },
      {
        "time": "Q1 10:40",
        "text": "Trey Murphy III blocks Donovan Mitchell 's 1-foot driving layup"
      },
      {
        "time": "Q1 10:46",
        "text": "Donovan Mitchell defensive rebound"
      }
    ]
  }
}